{
    "2015-12-03": {
        "1.0": 14.14,
        "13.0": 14.16,
        "15.0": 14.16,
        "26.0": 14.16,
        "32.0": 14.16,
        "43.0": 14.19,
        "56.0": 14.21,
        "60.0": 14.21,
        "76.0": 14.31,
        "88.0": 14.37,
        "90.0": 14.39,
        "105.0": 14.51,
        "110.0": 14.54,
        "120.0": 14.59,
        "134.0": 14.7,
        "148.0": 14.77,
        "165.0": 14.88,
        "181.0": 14.97,
        "197.0": 15.06,
        "210.0": 15.12,
        "225.0": 15.22,
        "239.0": 15.29,
        "256.0": 15.36,
        "270.0": 15.42,
        "272.0": 15.43,
        "280.0": 15.45,
        "294.0": 15.51,
        "302.0": 15.54,
        "315.0": 15.58,
        "330.0": 15.62,
        "334.0": 15.63,
        "349.0": 15.66,
        "361.0": 15.69,
        "364.0": 15.7,
        "378.0": 15.73,
        "390.0": 15.75,
        "396.0": 15.76,
        "420.0": 15.81,
        "440.0": 15.84,
        "460.0": 15.87,
        "480.0": 15.9,
        "496.0": 15.92,
        "510.0": 15.93,
        "529.0": 15.95,
        "546.0": 15.97,
        "571.0": 15.99,
        "592.0": 16.01,
        "607.0": 16.01,
        "622.0": 16.02,
        "638.0": 16.02,
        "652.0": 16.03,
        "669.0": 16.03,
        "690.0": 16.03,
        "714.0": 16.03,
        "729.0": 16.03,
        "761.0": 16.03,
        "781.0": 16.03,
        "810.0": 16.04,
        "833.0": 16.04,
        "851.0": 16.04,
        "872.0": 16.04,
        "894.0": 16.05,
        "930.0": 16.05,
        "956.0": 16.05,
        "972.0": 16.04,
        "991.0": 16.04,
        "1019.0": 16.04,
        "1033.0": 16.03,
        "1050.0": 16.03,
        "1082.0": 16.03,
        "1126.0": 16.02,
        "1140.0": 16.02,
        "1184.0": 16.0,
        "1201.0": 16.0,
        "1229.0": 15.99,
        "1259.0": 15.98,
        "1320.0": 15.96,
        "1383.0": 15.92,
        "1412.0": 15.91,
        "1446.0": 15.89,
        "1504.0": 15.86,
        "1551.0": 15.84,
        "1581.0": 15.83,
        "1625.0": 15.81,
        "1686.0": 15.78,
        "1719.0": 15.77,
        "1748.0": 15.76,
        "1778.0": 15.75,
        "1810.0": 15.74,
        "1870.0": 15.72,
        "1915.0": 15.72,
        "1946.0": 15.72,
        "1992.0": 15.72,
        "2051.0": 15.72,
        "2099.0": 15.72,
        "2129.0": 15.72,
        "2160.0": 15.72,
        "2223.0": 15.71,
        "2266.0": 15.71,
        "2311.0": 15.71,
        "2356.0": 15.71,
        "2416.0": 15.71,
        "2478.0": 15.71,
        "2510.0": 15.71,
        "2540.0": 15.71,
        "2601.0": 15.71,
        "2659.0": 15.71,
        "2692.0": 15.71,
        "2751.0": 15.71,
        "2783.0": 15.7,
        "2860.0": 15.7,
        "2881.0": 15.7,
        "2952.0": 15.7,
        "3056.0": 15.7,
        "3133.0": 15.69,
        "3240.0": 15.69,
        "3318.0": 15.69,
        "3451.0": 15.7,
        "3543.0": 15.7,
        "3637.0": 15.71,
        "3730.0": 15.71,
        "3863.0": 15.72,
        "3960.0": 15.72,
        "4050.0": 15.72,
        "4183.0": 15.73,
        "4274.0": 15.73,
        "4366.0": 15.73,
        "4457.0": 15.73,
        "4596.0": 15.74,
        "4680.0": 15.74,
        "4779.0": 15.74,
        "4912.0": 15.74,
        "4990.0": 15.74,
        "5040.0": 15.74,
        "5144.0": 15.74,
        "5233.0": 15.74,
        "5324.0": 15.74,
        "5401.0": 15.74,
        "5509.0": 15.74,
        "5580.0": 15.74,
        "5734.0": 15.74,
        "5919.0": 15.74,
        "6101.0": 15.74,
        "6284.0": 15.74,
        "6465.0": 15.74,
        "6649.0": 15.74,
        "6830.0": 15.74,
        "7014.0": 15.74,
        "7195.0": 15.74,
        "7379.0": 15.74,
        "7561.0": 15.74,
        "7748.0": 15.74,
        "7928.0": 15.74,
        "8110.0": 15.74,
        "8292.0": 15.74,
        "8475.0": 15.74,
        "8656.0": 15.74,
        "8840.0": 15.74,
        "9022.0": 15.74,
        "9206.0": 15.74,
        "9387.0": 15.74,
        "9575.0": 15.74,
        "9752.0": 15.74,
        "9937.0": 15.74,
        "10119.0": 15.74,
        "10301.0": 15.74,
        "10483.0": 15.74,
        "10667.0": 15.74,
        "10848.0": 15.74,
        "11213.0": 15.74,
        "11578.0": 15.74,
        "11946.0": 15.74,
        "12310.0": 15.74,
        "12674.0": 15.74,
        "12.0": 14.16,
        "14.0": 14.16,
        "25.0": 14.16,
        "27.0": 14.16,
        "33.0": 14.17,
        "47.0": 14.2,
        "57.0": 14.21,
        "74.0": 14.3,
        "85.0": 14.36,
        "89.0": 14.38,
        "103.0": 14.49,
        "106.0": 14.52,
        "119.0": 14.58,
        "132.0": 14.68,
        "147.0": 14.76,
        "151.0": 14.78,
        "180.0": 14.96,
        "195.0": 15.05,
        "209.0": 15.12,
        "211.0": 15.13,
        "238.0": 15.29,
        "242.0": 15.3,
        "258.0": 15.37,
        "271.0": 15.42,
        "273.0": 15.43,
        "287.0": 15.48,
        "300.0": 15.53,
        "305.0": 15.55,
        "319.0": 15.58,
        "333.0": 15.62,
        "336.0": 15.63,
        "354.0": 15.67,
        "363.0": 15.69,
        "377.0": 15.72,
        "384.0": 15.74,
        "392.0": 15.76,
        "410.0": 15.79,
        "426.0": 15.82,
        "454.0": 15.86,
        "468.0": 15.88,
        "487.0": 15.9,
        "501.0": 15.92,
        "516.0": 15.94,
        "540.0": 15.96,
        "559.0": 15.98,
        "578.0": 16.0,
        "600.0": 16.01,
        "621.0": 16.02,
        "630.0": 16.02,
        "645.0": 16.02,
        "662.0": 16.03,
        "683.0": 16.03,
        "699.0": 16.03,
        "720.0": 16.03,
        "750.0": 16.03,
        "774.0": 16.03,
        "805.0": 16.04,
        "819.0": 16.04,
        "840.0": 16.04,
        "865.0": 16.04,
        "881.0": 16.04,
        "900.0": 16.05,
        "942.0": 16.05,
        "960.0": 16.05,
        "986.0": 16.04,
        "1005.0": 16.04,
        "1020.0": 16.04,
        "1047.0": 16.03,
        "1079.0": 16.03,
        "1110.0": 16.02,
        "1139.0": 16.02,
        "1170.0": 16.01,
        "1198.0": 16.0,
        "1215.0": 15.99,
        "1246.0": 15.99,
        "1306.0": 15.97,
        "1351.0": 15.94,
        "1398.0": 15.92,
        "1440.0": 15.89,
        "1491.0": 15.87,
        "1537.0": 15.85,
        "1565.0": 15.83,
        "1595.0": 15.82,
        "1672.0": 15.79,
        "1705.0": 15.78,
        "1734.0": 15.76,
        "1764.0": 15.75,
        "1800.0": 15.74,
        "1859.0": 15.72,
        "1903.0": 15.72,
        "1929.0": 15.72,
        "1960.0": 15.72,
        "2037.0": 15.72,
        "2083.0": 15.72,
        "2113.0": 15.72,
        "2143.0": 15.72,
        "2175.0": 15.72,
        "2237.0": 15.71,
        "2294.0": 15.71,
        "2328.0": 15.71,
        "2402.0": 15.71,
        "2447.0": 15.71,
        "2496.0": 15.71,
        "2520.0": 15.71,
        "2587.0": 15.71,
        "2631.0": 15.71,
        "2678.0": 15.71,
        "2720.0": 15.71,
        "2769.0": 15.7,
        "2812.0": 15.7,
        "2874.0": 15.7,
        "2905.0": 15.7,
        "2996.0": 15.7,
        "3086.0": 15.7,
        "3178.0": 15.69,
        "3273.0": 15.69,
        "3364.0": 15.69,
        "3498.0": 15.7,
        "3602.0": 15.71,
        "3683.0": 15.71,
        "3816.0": 15.72,
        "3910.0": 15.72,
        "4001.0": 15.72,
        "4092.0": 15.72,
        "4228.0": 15.73,
        "4320.0": 15.73,
        "4414.0": 15.73,
        "4547.0": 15.74,
        "4639.0": 15.74,
        "4732.0": 15.74,
        "4823.0": 15.74,
        "4960.0": 15.74,
        "5004.0": 15.74,
        "5097.0": 15.74,
        "5188.0": 15.74,
        "5277.0": 15.74,
        "5369.0": 15.74,
        "5464.0": 15.74,
        "5555.0": 15.74,
        "5642.0": 15.74,
        "5828.0": 15.74,
        "6010.0": 15.74,
        "6193.0": 15.74,
        "6374.0": 15.74,
        "6558.0": 15.74,
        "6738.0": 15.74,
        "6923.0": 15.74,
        "7103.0": 15.74,
        "7288.0": 15.74,
        "7469.0": 15.74,
        "7655.0": 15.74,
        "7834.0": 15.74,
        "8019.0": 15.74,
        "8201.0": 15.74,
        "8384.0": 15.74,
        "8565.0": 15.74,
        "8749.0": 15.74,
        "8930.0": 15.74,
        "9115.0": 15.74,
        "9295.0": 15.74,
        "9482.0": 15.74,
        "9660.0": 15.74,
        "9846.0": 15.74,
        "10025.0": 15.74,
        "10210.0": 15.74,
        "10392.0": 15.74,
        "10576.0": 15.74,
        "10756.0": 15.74,
        "11032.0": 15.74,
        "11397.0": 15.74,
        "11766.0": 15.74,
        "12128.0": 15.74,
        "12493.0": 15.74,
        "14410.0": 15.74
    }
}