{
    "2017-03-17": {
        "3.0": 12.13,
        "6.0": 12.13,
        "14.0": 12.13,
        "26.0": 11.94,
        "32.0": 11.89,
        "41.0": 11.83,
        "46.0": 11.82,
        "60.0": 11.65,
        "63.0": 11.61,
        "75.0": 11.54,
        "89.0": 11.35,
        "104.0": 11.2,
        "108.0": 11.18,
        "122.0": 11.06,
        "133.0": 10.97,
        "137.0": 10.95,
        "151.0": 10.82,
        "166.0": 10.7,
        "168.0": 10.68,
        "180.0": 10.6,
        "188.0": 10.54,
        "199.0": 10.47,
        "213.0": 10.4,
        "215.0": 10.38,
        "228.0": 10.32,
        "241.0": 10.25,
        "258.0": 10.15,
        "270.0": 10.09,
        "273.0": 10.07,
        "285.0": 10.03,
        "291.0": 10.01,
        "304.0": 9.96,
        "321.0": 9.9,
        "335.0": 9.88,
        "349.0": 9.85,
        "363.0": 9.81,
        "381.0": 9.77,
        "395.0": 9.74,
        "406.0": 9.72,
        "420.0": 9.7,
        "451.0": 9.66,
        "472.0": 9.63,
        "486.0": 9.62,
        "510.0": 9.6,
        "535.0": 9.59,
        "549.0": 9.58,
        "563.0": 9.57,
        "577.0": 9.57,
        "600.0": 9.56,
        "630.0": 9.55,
        "641.0": 9.54,
        "661.0": 9.54,
        "690.0": 9.57,
        "714.0": 9.58,
        "728.0": 9.59,
        "752.0": 9.6,
        "776.0": 9.62,
        "789.0": 9.63,
        "836.0": 9.65,
        "850.0": 9.66,
        "881.0": 9.68,
        "913.0": 9.7,
        "928.0": 9.71,
        "942.0": 9.71,
        "976.0": 9.73,
        "1021.0": 9.75,
        "1050.0": 9.78,
        "1081.0": 9.8,
        "1110.0": 9.83,
        "1125.0": 9.84,
        "1155.0": 9.87,
        "1200.0": 9.9,
        "1216.0": 9.91,
        "1249.0": 9.92,
        "1278.0": 9.93,
        "1308.0": 9.95,
        "1389.0": 9.97,
        "1433.0": 9.99,
        "1445.0": 9.99,
        "1476.0": 10.01,
        "1508.0": 10.03,
        "1567.0": 10.07,
        "1613.0": 10.08,
        "1643.0": 10.08,
        "1673.0": 10.09,
        "1753.0": 10.13,
        "1796.0": 10.15,
        "1811.0": 10.15,
        "1841.0": 10.16,
        "1886.0": 10.17,
        "1946.0": 10.19,
        "1994.0": 10.2,
        "2026.0": 10.21,
        "2070.0": 10.22,
        "2131.0": 10.23,
        "2161.0": 10.24,
        "2189.0": 10.24,
        "2222.0": 10.24,
        "2281.0": 10.25,
        "2313.0": 10.26,
        "2390.0": 10.27,
        "2435.0": 10.27,
        "2520.0": 10.28,
        "2586.0": 10.29,
        "2663.0": 10.3,
        "2803.0": 10.32,
        "2880.0": 10.33,
        "2968.0": 10.34,
        "3028.0": 10.34,
        "3167.0": 10.35,
        "3240.0": 10.36,
        "3346.0": 10.38,
        "3440.0": 10.39,
        "3580.0": 10.41,
        "3622.0": 10.41,
        "3758.0": 10.42,
        "3896.0": 10.43,
        "3960.0": 10.43,
        "4077.0": 10.44,
        "4169.0": 10.44,
        "4309.0": 10.45,
        "4353.0": 10.45,
        "4490.0": 10.46,
        "4534.0": 10.46,
        "4674.0": 10.47,
        "4718.0": 10.47,
        "4807.0": 10.47,
        "4899.0": 10.48,
        "5039.0": 10.48,
        "5085.0": 10.48,
        "5264.0": 10.49,
        "5400.0": 10.49,
        "5540.0": 10.5,
        "5631.0": 10.5,
        "5814.0": 10.51,
        "5995.0": 10.51,
        "6179.0": 10.52,
        "6360.0": 10.52,
        "6544.0": 10.53,
        "6725.0": 10.53,
        "6909.0": 10.53,
        "7091.0": 10.54,
        "7200.0": 10.54,
        "7364.0": 10.54,
        "7549.0": 10.55,
        "7731.0": 10.55,
        "7914.0": 10.55,
        "8095.0": 10.56,
        "8279.0": 10.56,
        "8460.0": 10.56,
        "8645.0": 10.56,
        "8825.0": 10.57,
        "9000.0": 10.57,
        "9105.0": 10.57,
        "9282.0": 10.57,
        "9467.0": 10.57,
        "9649.0": 10.58,
        "9831.0": 10.58,
        "10013.0": 10.58,
        "10197.0": 10.58,
        "10378.0": 10.58,
        "10743.0": 10.59,
        "10927.0": 10.59,
        "11296.0": 10.59,
        "11658.0": 10.59,
        "12023.0": 10.6,
        "13940.0": 10.61,
        "4.0": 12.13,
        "13.0": 12.13,
        "17.0": 12.13,
        "31.0": 11.91,
        "33.0": 11.88,
        "42.0": 11.83,
        "59.0": 11.66,
        "61.0": 11.64,
        "67.0": 11.59,
        "76.0": 11.53,
        "91.0": 11.33,
        "105.0": 11.19,
        "117.0": 11.09,
        "126.0": 11.01,
        "136.0": 10.96,
        "150.0": 10.83,
        "152.0": 10.81,
        "167.0": 10.69,
        "175.0": 10.64,
        "182.0": 10.58,
        "196.0": 10.48,
        "210.0": 10.4,
        "214.0": 10.39,
        "227.0": 10.32,
        "229.0": 10.31,
        "244.0": 10.23,
        "259.0": 10.15,
        "271.0": 10.09,
        "277.0": 10.06,
        "286.0": 10.02,
        "300.0": 9.97,
        "320.0": 9.9,
        "334.0": 9.88,
        "347.0": 9.86,
        "360.0": 9.82,
        "369.0": 9.8,
        "390.0": 9.75,
        "397.0": 9.74,
        "411.0": 9.72,
        "424.0": 9.7,
        "453.0": 9.65,
        "480.0": 9.62,
        "502.0": 9.61,
        "516.0": 9.6,
        "542.0": 9.58,
        "552.0": 9.58,
        "570.0": 9.57,
        "579.0": 9.56,
        "609.0": 9.55,
        "635.0": 9.55,
        "656.0": 9.54,
        "669.0": 9.55,
        "700.0": 9.57,
        "720.0": 9.59,
        "745.0": 9.6,
        "759.0": 9.61,
        "780.0": 9.62,
        "810.0": 9.64,
        "840.0": 9.65,
        "871.0": 9.67,
        "900.0": 9.69,
        "917.0": 9.7,
        "930.0": 9.71,
        "962.0": 9.72,
        "990.0": 9.74,
        "1034.0": 9.76,
        "1067.0": 9.79,
        "1095.0": 9.82,
        "1111.0": 9.83,
        "1140.0": 9.85,
        "1172.0": 9.88,
        "1202.0": 9.9,
        "1235.0": 9.92,
        "1264.0": 9.93,
        "1294.0": 9.94,
        "1340.0": 9.96,
        "1400.0": 9.98,
        "1440.0": 9.99,
        "1459.0": 10.0,
        "1490.0": 10.02,
        "1522.0": 10.04,
        "1581.0": 10.07,
        "1629.0": 10.08,
        "1659.0": 10.08,
        "1705.0": 10.1,
        "1767.0": 10.14,
        "1802.0": 10.15,
        "1824.0": 10.15,
        "1858.0": 10.16,
        "1932.0": 10.18,
        "1977.0": 10.2,
        "2008.0": 10.2,
        "2040.0": 10.21,
        "2117.0": 10.23,
        "2160.0": 10.24,
        "2175.0": 10.24,
        "2208.0": 10.24,
        "2250.0": 10.25,
        "2299.0": 10.25,
        "2342.0": 10.26,
        "2404.0": 10.27,
        "2482.0": 10.28,
        "2526.0": 10.28,
        "2616.0": 10.3,
        "2708.0": 10.31,
        "2848.0": 10.33,
        "2894.0": 10.33,
        "2981.0": 10.34,
        "3073.0": 10.35,
        "3213.0": 10.36,
        "3260.0": 10.36,
        "3393.0": 10.38,
        "3531.0": 10.4,
        "3601.0": 10.41,
        "3713.0": 10.42,
        "3804.0": 10.42,
        "3944.0": 10.43,
        "3987.0": 10.43,
        "4126.0": 10.44,
        "4262.0": 10.45,
        "4322.0": 10.45,
        "4442.0": 10.45,
        "4520.0": 10.46,
        "4627.0": 10.46,
        "4680.0": 10.47,
        "4763.0": 10.47,
        "4854.0": 10.47,
        "4994.0": 10.48,
        "5040.0": 10.48,
        "5172.0": 10.49,
        "5358.0": 10.49,
        "5449.0": 10.5,
        "5582.0": 10.5,
        "5723.0": 10.5,
        "5904.0": 10.51,
        "6088.0": 10.52,
        "6268.0": 10.52,
        "6453.0": 10.52,
        "6633.0": 10.53,
        "6818.0": 10.53,
        "6999.0": 10.54,
        "7185.0": 10.54,
        "7278.0": 10.54,
        "7458.0": 10.55,
        "7640.0": 10.55,
        "7822.0": 10.55,
        "8005.0": 10.55,
        "8186.0": 10.56,
        "8370.0": 10.56,
        "8552.0": 10.56,
        "8736.0": 10.56,
        "8917.0": 10.57,
        "9012.0": 10.57,
        "9190.0": 10.57,
        "9376.0": 10.57,
        "9555.0": 10.57,
        "9740.0": 10.58,
        "9922.0": 10.58,
        "10106.0": 10.58,
        "10286.0": 10.58,
        "10562.0": 10.58,
        "10800.0": 10.59,
        "11108.0": 10.59,
        "11476.0": 10.59,
        "11840.0": 10.59,
        "12204.0": 10.6
    }
}