{
    "2021-11-09": {
        "1.0": 7.65,
        "10.0": 7.68,
        "20.0": 7.68,
        "22.0": 7.68,
        "31.0": 8.08,
        "36.0": 8.19,
        "38.0": 8.25,
        "50.0": 8.41,
        "55.0": 8.45,
        "69.0": 8.64,
        "84.0": 8.78,
        "98.0": 9.12,
        "107.0": 9.31,
        "113.0": 9.36,
        "122.0": 9.6,
        "128.0": 9.71,
        "134.0": 9.82,
        "143.0": 9.99,
        "155.0": 10.23,
        "170.0": 10.46,
        "174.0": 10.51,
        "188.0": 10.71,
        "203.0": 10.89,
        "210.0": 10.98,
        "220.0": 11.09,
        "233.0": 11.23,
        "240.0": 11.29,
        "248.0": 11.36,
        "262.0": 11.46,
        "272.0": 11.52,
        "281.0": 11.58,
        "295.0": 11.66,
        "300.0": 11.69,
        "317.0": 11.79,
        "328.0": 11.84,
        "335.0": 11.87,
        "342.0": 11.89,
        "356.0": 11.94,
        "360.0": 11.96,
        "386.0": 12.04,
        "391.0": 12.05,
        "407.0": 12.1,
        "419.0": 12.14,
        "433.0": 12.15,
        "463.0": 12.17,
        "482.0": 12.18,
        "510.0": 12.2,
        "524.0": 12.2,
        "540.0": 12.21,
        "570.0": 12.21,
        "583.0": 12.21,
        "601.0": 12.22,
        "630.0": 12.18,
        "645.0": 12.17,
        "661.0": 12.15,
        "681.0": 12.14,
        "706.0": 12.11,
        "720.0": 12.09,
        "750.0": 12.06,
        "780.0": 12.02,
        "811.0": 12.01,
        "840.0": 12.0,
        "874.0": 11.99,
        "902.0": 11.98,
        "930.0": 11.96,
        "965.0": 11.95,
        "1010.0": 11.92,
        "1050.0": 11.9,
        "1066.0": 11.89,
        "1105.0": 11.87,
        "1140.0": 11.85,
        "1170.0": 11.84,
        "1200.0": 11.84,
        "1270.0": 11.8,
        "1330.0": 11.75,
        "1422.0": 11.76,
        "1469.0": 11.74,
        "1562.0": 11.74,
        "1648.0": 11.72,
        "1742.0": 11.71,
        "1800.0": 11.72,
        "1882.0": 11.72,
        "2015.0": 11.76,
        "2106.0": 11.78,
        "2198.0": 11.8,
        "2289.0": 11.8,
        "2428.0": 11.76,
        "2520.0": 11.73,
        "2611.0": 11.71,
        "2744.0": 11.72,
        "2822.0": 11.73,
        "2880.0": 11.74,
        "2976.0": 11.75,
        "3065.0": 11.72,
        "3156.0": 11.7,
        "3240.0": 11.68,
        "3341.0": 11.66,
        "3474.0": 11.66,
        "3600.0": 11.66,
        "3751.0": 11.67,
        "3933.0": 11.67,
        "4025.0": 11.67,
        "4116.0": 11.67,
        "4297.0": 11.67,
        "4390.0": 11.66,
        "4570.0": 11.66,
        "4682.0": 11.66,
        "4802.0": 11.66,
        "4935.0": 11.66,
        "5040.0": 11.66,
        "5167.0": 11.66,
        "5301.0": 11.68,
        "5400.0": 11.71,
        "5533.0": 11.73,
        "5666.0": 11.76,
        "5851.0": 11.79,
        "6033.0": 11.82,
        "6216.0": 11.85,
        "6397.0": 11.88,
        "6581.0": 11.91,
        "6762.0": 11.93,
        "6947.0": 11.96,
        "7127.0": 11.98,
        "7219.0": 11.99,
        "7407.0": 12.01,
        "7584.0": 12.03,
        "7769.0": 12.05,
        "7951.0": 12.07,
        "8133.0": 12.08,
        "8315.0": 12.1,
        "8499.0": 12.12,
        "8680.0": 12.13,
        "9001.0": 12.15,
        "9229.0": 12.17,
        "9598.0": 12.2,
        "9960.0": 12.22,
        "10325.0": 12.24,
        "10800.0": 12.27,
        "7.0": 7.67,
        "14.0": 7.68,
        "21.0": 7.68,
        "30.0": 8.04,
        "34.0": 8.12,
        "37.0": 8.22,
        "42.0": 8.29,
        "51.0": 8.42,
        "62.0": 8.56,
        "83.0": 8.77,
        "90.0": 8.93,
        "99.0": 9.15,
        "108.0": 9.34,
        "120.0": 9.53,
        "126.0": 9.66,
        "129.0": 9.74,
        "142.0": 9.97,
        "150.0": 10.14,
        "160.0": 10.28,
        "171.0": 10.48,
        "181.0": 10.61,
        "195.0": 10.79,
        "204.0": 10.91,
        "218.0": 11.08,
        "232.0": 11.21,
        "234.0": 11.24,
        "246.0": 11.33,
        "261.0": 11.45,
        "265.0": 11.47,
        "279.0": 11.56,
        "294.0": 11.65,
        "296.0": 11.67,
        "310.0": 11.75,
        "325.0": 11.83,
        "330.0": 11.85,
        "338.0": 11.88,
        "353.0": 11.94,
        "357.0": 11.95,
        "372.0": 11.99,
        "387.0": 12.04,
        "400.0": 12.08,
        "415.0": 12.13,
        "420.0": 12.14,
        "450.0": 12.16,
        "477.0": 12.18,
        "491.0": 12.19,
        "519.0": 12.2,
        "534.0": 12.2,
        "552.0": 12.21,
        "582.0": 12.21,
        "597.0": 12.22,
        "615.0": 12.2,
        "644.0": 12.17,
        "660.0": 12.16,
        "675.0": 12.14,
        "692.0": 12.13,
        "708.0": 12.11,
        "737.0": 12.07,
        "764.0": 12.04,
        "784.0": 12.02,
        "828.0": 12.0,
        "870.0": 11.99,
        "888.0": 11.98,
        "918.0": 11.97,
        "960.0": 11.95,
        "990.0": 11.94,
        "1021.0": 11.92,
        "1057.0": 11.9,
        "1080.0": 11.89,
        "1112.0": 11.87,
        "1150.0": 11.85,
        "1196.0": 11.84,
        "1239.0": 11.83,
        "1283.0": 11.79,
        "1375.0": 11.75,
        "1441.0": 11.75,
        "1515.0": 11.73,
        "1604.0": 11.75,
        "1695.0": 11.7,
        "1787.0": 11.72,
        "1833.0": 11.72,
        "1924.0": 11.73,
        "2060.0": 11.77,
        "2162.0": 11.8,
        "2246.0": 11.82,
        "2379.0": 11.77,
        "2471.0": 11.75,
        "2564.0": 11.72,
        "2655.0": 11.72,
        "2792.0": 11.73,
        "2836.0": 11.73,
        "2929.0": 11.74,
        "3020.0": 11.73,
        "3109.0": 11.71,
        "3201.0": 11.69,
        "3296.0": 11.67,
        "3387.0": 11.66,
        "3566.0": 11.66,
        "3660.0": 11.67,
        "3842.0": 11.67,
        "3961.0": 11.67,
        "4073.0": 11.67,
        "4206.0": 11.67,
        "4321.0": 11.66,
        "4481.0": 11.66,
        "4662.0": 11.66,
        "4755.0": 11.66,
        "4846.0": 11.66,
        "5027.0": 11.66,
        "5120.0": 11.66,
        "5211.0": 11.67,
        "5393.0": 11.7,
        "5487.0": 11.72,
        "5580.0": 11.74,
        "5760.0": 11.78,
        "5942.0": 11.81,
        "6124.0": 11.84,
        "6307.0": 11.87,
        "6488.0": 11.89,
        "6672.0": 11.92,
        "6854.0": 11.94,
        "7038.0": 11.97,
        "7202.0": 11.99,
        "7314.0": 12.0,
        "7492.0": 12.02,
        "7678.0": 12.04,
        "7857.0": 12.06,
        "8042.0": 12.07,
        "8224.0": 12.09,
        "8408.0": 12.11,
        "8588.0": 12.12,
        "8864.0": 12.14,
        "9045.0": 12.16,
        "9410.0": 12.18,
        "9778.0": 12.21,
        "10142.0": 12.23,
        "10506.0": 12.25,
        "12242.0": 12.33
    }
}