{
    "2018-02-20": {
        "1.0": 6.64,
        "7.0": 6.65,
        "9.0": 6.64,
        "23.0": 1.68,
        "28.0": 2.4,
        "30.0": 2.78,
        "36.0": 3.36,
        "41.0": 3.59,
        "57.0": 2.78,
        "62.0": 3.04,
        "69.0": 3.4,
        "84.0": 2.69,
        "90.0": 2.93,
        "99.0": 3.28,
        "113.0": 2.87,
        "120.0": 2.9,
        "128.0": 3.14,
        "132.0": 3.21,
        "150.0": 3.01,
        "160.0": 3.19,
        "162.0": 3.25,
        "181.0": 3.02,
        "192.0": 3.25,
        "209.0": 3.43,
        "212.0": 3.49,
        "220.0": 3.61,
        "237.0": 3.49,
        "240.0": 3.55,
        "253.0": 3.7,
        "269.0": 3.15,
        "283.0": 3.33,
        "295.0": 3.0,
        "301.0": 2.88,
        "310.0": 2.99,
        "316.0": 3.04,
        "330.0": 2.57,
        "345.0": 2.79,
        "358.0": 2.48,
        "372.0": 2.57,
        "388.0": 2.64,
        "405.0": 2.67,
        "420.0": 2.71,
        "436.0": 2.74,
        "450.0": 2.77,
        "482.0": 2.92,
        "510.0": 3.04,
        "541.0": 3.16,
        "573.0": 3.27,
        "588.0": 3.31,
        "602.0": 3.36,
        "630.0": 3.43,
        "660.0": 3.51,
        "681.0": 3.55,
        "694.0": 3.58,
        "722.0": 3.64,
        "741.0": 3.67,
        "755.0": 3.7,
        "783.0": 3.75,
        "811.0": 3.79,
        "840.0": 3.84,
        "870.0": 3.88,
        "895.0": 3.91,
        "909.0": 3.93,
        "931.0": 3.95,
        "954.0": 3.98,
        "968.0": 3.99,
        "1000.0": 4.02,
        "1049.0": 4.06,
        "1060.0": 4.07,
        "1093.0": 4.1,
        "1112.0": 4.11,
        "1136.0": 4.13,
        "1150.0": 4.14,
        "1170.0": 4.15,
        "1200.0": 4.18,
        "1241.0": 4.23,
        "1289.0": 4.29,
        "1319.0": 4.32,
        "1365.0": 4.36,
        "1427.0": 4.41,
        "1456.0": 4.44,
        "1484.0": 4.46,
        "1518.0": 4.49,
        "1592.0": 4.54,
        "1637.0": 4.57,
        "1668.0": 4.59,
        "1700.0": 4.61,
        "1777.0": 4.65,
        "1800.0": 4.67,
        "1835.0": 4.68,
        "1868.0": 4.7,
        "1910.0": 4.72,
        "1959.0": 4.73,
        "2002.0": 4.73,
        "2050.0": 4.74,
        "2095.0": 4.75,
        "2162.0": 4.76,
        "2246.0": 4.77,
        "2323.0": 4.77,
        "2463.0": 4.79,
        "2520.0": 4.8,
        "2628.0": 4.82,
        "2688.0": 4.83,
        "2827.0": 4.84,
        "2880.0": 4.85,
        "3006.0": 4.86,
        "3100.0": 4.87,
        "3240.0": 4.89,
        "3373.0": 4.9,
        "3464.0": 4.91,
        "3600.0": 4.93,
        "3647.0": 4.93,
        "3786.0": 4.95,
        "3922.0": 4.96,
        "3969.0": 4.97,
        "4102.0": 4.98,
        "4180.0": 4.99,
        "4287.0": 5.0,
        "4334.0": 5.01,
        "4423.0": 5.02,
        "4514.0": 5.03,
        "4654.0": 5.03,
        "4699.0": 5.03,
        "4832.0": 5.03,
        "5018.0": 5.03,
        "5109.0": 5.03,
        "5291.0": 5.03,
        "5400.0": 5.03,
        "5564.0": 5.03,
        "5655.0": 5.03,
        "5839.0": 5.03,
        "6020.0": 5.03,
        "6204.0": 5.03,
        "6385.0": 5.03,
        "6569.0": 5.03,
        "6751.0": 5.03,
        "6938.0": 5.03,
        "7118.0": 5.03,
        "7209.0": 5.03,
        "7391.0": 5.03,
        "7574.0": 5.03,
        "7755.0": 5.03,
        "7939.0": 5.03,
        "8120.0": 5.03,
        "8305.0": 5.03,
        "8485.0": 5.03,
        "8672.0": 5.03,
        "8850.0": 5.03,
        "9001.0": 5.03,
        "9127.0": 5.03,
        "9309.0": 5.03,
        "9491.0": 5.03,
        "9673.0": 5.03,
        "9857.0": 5.03,
        "10038.0": 5.03,
        "10403.0": 5.03,
        "10768.0": 5.03,
        "10956.0": 5.03,
        "11318.0": 5.03,
        "11683.0": 5.03,
        "13600.0": 5.03,
        "2.0": 6.65,
        "8.0": 6.65,
        "22.0": 1.89,
        "24.0": 1.95,
        "29.0": 2.6,
        "34.0": 3.09,
        "37.0": 3.48,
        "55.0": 2.59,
        "58.0": 2.87,
        "66.0": 3.33,
        "71.0": 3.46,
        "85.0": 2.75,
        "91.0": 2.98,
        "101.0": 3.32,
        "115.0": 2.77,
        "121.0": 2.94,
        "129.0": 3.18,
        "146.0": 2.87,
        "153.0": 3.04,
        "161.0": 3.22,
        "176.0": 2.94,
        "191.0": 3.23,
        "195.0": 3.28,
        "210.0": 3.45,
        "213.0": 3.51,
        "223.0": 3.62,
        "239.0": 3.53,
        "252.0": 3.68,
        "254.0": 3.72,
        "272.0": 3.17,
        "286.0": 3.35,
        "300.0": 2.86,
        "304.0": 2.93,
        "311.0": 3.01,
        "329.0": 2.55,
        "335.0": 2.63,
        "346.0": 2.75,
        "360.0": 2.42,
        "374.0": 2.61,
        "391.0": 2.64,
        "419.0": 2.7,
        "421.0": 2.71,
        "449.0": 2.76,
        "477.0": 2.9,
        "496.0": 2.98,
        "540.0": 3.15,
        "570.0": 3.26,
        "577.0": 3.28,
        "601.0": 3.35,
        "603.0": 3.36,
        "636.0": 3.45,
        "666.0": 3.52,
        "692.0": 3.57,
        "720.0": 3.63,
        "727.0": 3.65,
        "750.0": 3.69,
        "771.0": 3.73,
        "785.0": 3.75,
        "815.0": 3.8,
        "862.0": 3.87,
        "876.0": 3.89,
        "902.0": 3.92,
        "924.0": 3.95,
        "938.0": 3.96,
        "960.0": 3.98,
        "990.0": 4.01,
        "1021.0": 4.04,
        "1050.0": 4.06,
        "1080.0": 4.09,
        "1105.0": 4.11,
        "1119.0": 4.12,
        "1140.0": 4.13,
        "1168.0": 4.15,
        "1182.0": 4.16,
        "1227.0": 4.22,
        "1273.0": 4.27,
        "1303.0": 4.3,
        "1333.0": 4.33,
        "1413.0": 4.4,
        "1441.0": 4.43,
        "1471.0": 4.45,
        "1501.0": 4.47,
        "1546.0": 4.51,
        "1606.0": 4.55,
        "1654.0": 4.58,
        "1686.0": 4.6,
        "1730.0": 4.63,
        "1791.0": 4.66,
        "1821.0": 4.68,
        "1849.0": 4.69,
        "1882.0": 4.71,
        "1941.0": 4.73,
        "1973.0": 4.73,
        "2019.0": 4.74,
        "2064.0": 4.74,
        "2142.0": 4.75,
        "2186.0": 4.76,
        "2276.0": 4.77,
        "2368.0": 4.78,
        "2508.0": 4.8,
        "2554.0": 4.81,
        "2641.0": 4.82,
        "2733.0": 4.83,
        "2873.0": 4.85,
        "2920.0": 4.85,
        "3053.0": 4.87,
        "3191.0": 4.88,
        "3282.0": 4.89,
        "3418.0": 4.91,
        "3556.0": 4.92,
        "3604.0": 4.93,
        "3737.0": 4.94,
        "3829.0": 4.95,
        "3962.0": 4.97,
        "4013.0": 4.97,
        "4150.0": 4.99,
        "4194.0": 4.99,
        "4320.0": 5.01,
        "4378.0": 5.01,
        "4467.0": 5.02,
        "4559.0": 5.03,
        "4682.0": 5.03,
        "4745.0": 5.03,
        "4924.0": 5.03,
        "5040.0": 5.03,
        "5200.0": 5.03,
        "5383.0": 5.03,
        "5474.0": 5.03,
        "5580.0": 5.03,
        "5748.0": 5.03,
        "5928.0": 5.03,
        "6113.0": 5.03,
        "6293.0": 5.03,
        "6478.0": 5.03,
        "6659.0": 5.03,
        "6845.0": 5.03,
        "7024.0": 5.03,
        "7202.0": 5.03,
        "7300.0": 5.03,
        "7482.0": 5.03,
        "7665.0": 5.03,
        "7846.0": 5.03,
        "8030.0": 5.03,
        "8212.0": 5.03,
        "8396.0": 5.03,
        "8577.0": 5.03,
        "8765.0": 5.03,
        "8942.0": 5.03,
        "9036.0": 5.03,
        "9215.0": 5.03,
        "9400.0": 5.03,
        "9582.0": 5.03,
        "9766.0": 5.03,
        "9946.0": 5.03,
        "10222.0": 5.03,
        "10587.0": 5.03,
        "10800.0": 5.03,
        "11136.0": 5.03,
        "11500.0": 5.03,
        "11864.0": 5.03
    }
}