{
    "2023-07-06": {
        "1.0": 13.65,
        "7.0": 17.14,
        "14.0": 16.26,
        "21.0": 15.38,
        "25.0": 15.18,
        "32.0": 14.77,
        "40.0": 11.06,
        "43.0": 11.28,
        "56.0": 11.74,
        "60.0": 11.81,
        "69.0": 10.67,
        "77.0": 10.56,
        "88.0": 10.85,
        "102.0": 10.04,
        "106.0": 10.18,
        "117.0": 10.4,
        "120.0": 10.45,
        "147.0": 9.74,
        "151.0": 9.78,
        "160.0": 8.36,
        "166.0": 8.48,
        "174.0": 8.63,
        "180.0": 8.71,
        "195.0": 7.54,
        "210.0": 7.84,
        "224.0": 7.15,
        "237.0": 7.37,
        "239.0": 7.41,
        "251.0": 6.98,
        "258.0": 6.92,
        "270.0": 7.07,
        "285.0": 6.63,
        "298.0": 6.8,
        "301.0": 6.83,
        "321.0": 6.49,
        "333.0": 6.59,
        "342.0": 6.24,
        "357.0": 5.9,
        "375.0": 5.56,
        "390.0": 5.27,
        "406.0": 4.99,
        "438.0": 4.88,
        "442.0": 4.86,
        "453.0": 4.83,
        "468.0": 4.78,
        "496.0": 4.71,
        "510.0": 4.67,
        "533.0": 4.62,
        "546.0": 4.6,
        "571.0": 4.55,
        "600.0": 4.49,
        "635.0": 4.44,
        "662.0": 4.4,
        "679.0": 4.38,
        "720.0": 4.38,
        "750.0": 4.38,
        "771.0": 4.38,
        "810.0": 4.38,
        "840.0": 4.38,
        "872.0": 4.37,
        "911.0": 4.37,
        "958.0": 4.37,
        "991.0": 4.37,
        "1021.0": 4.37,
        "1050.0": 4.37,
        "1091.0": 4.37,
        "1138.0": 4.37,
        "1170.0": 4.4,
        "1201.0": 4.43,
        "1278.0": 4.49,
        "1365.0": 4.56,
        "1440.0": 4.61,
        "1502.0": 4.65,
        "1594.0": 4.7,
        "1685.0": 4.74,
        "1775.0": 4.78,
        "1824.0": 4.8,
        "1960.0": 4.79,
        "2051.0": 4.76,
        "2160.0": 4.73,
        "2218.0": 4.71,
        "2325.0": 4.69,
        "2416.0": 4.67,
        "2505.0": 4.65,
        "2552.0": 4.64,
        "2692.0": 4.65,
        "2783.0": 4.66,
        "2881.0": 4.68,
        "3056.0": 4.7,
        "3147.0": 4.71,
        "3240.0": 4.72,
        "3421.0": 4.74,
        "3512.0": 4.75,
        "3693.0": 4.77,
        "3833.0": 4.78,
        "3960.0": 4.79,
        "4058.0": 4.8,
        "4198.0": 4.81,
        "4320.0": 4.82,
        "4423.0": 4.82,
        "4563.0": 4.82,
        "4680.0": 4.82,
        "4789.0": 4.82,
        "4929.0": 4.82,
        "5040.0": 4.82,
        "5156.0": 4.82,
        "5296.0": 4.82,
        "5401.0": 4.82,
        "5520.0": 4.82,
        "5612.0": 4.82,
        "5793.0": 4.82,
        "5977.0": 4.82,
        "6158.0": 4.82,
        "6343.0": 4.82,
        "6523.0": 4.82,
        "6710.0": 4.82,
        "6888.0": 4.82,
        "7074.0": 4.82,
        "7200.0": 4.82,
        "7347.0": 4.82,
        "7529.0": 4.82,
        "7711.0": 4.82,
        "7895.0": 4.82,
        "8076.0": 4.82,
        "8441.0": 4.82,
        "8806.0": 4.82,
        "9000.0": 4.82,
        "9356.0": 4.82,
        "9721.0": 4.82,
        "10800.0": 4.82,
        "13556.0": 4.82,
        "6.0": 16.92,
        "11.0": 17.39,
        "15.0": 16.02,
        "22.0": 15.27,
        "26.0": 15.09,
        "33.0": 14.01,
        "41.0": 11.14,
        "55.0": 11.7,
        "57.0": 11.78,
        "64.0": 11.2,
        "71.0": 10.35,
        "85.0": 10.81,
        "90.0": 10.91,
        "104.0": 10.11,
        "116.0": 10.37,
        "118.0": 10.43,
        "133.0": 9.46,
        "148.0": 9.76,
        "155.0": 8.94,
        "162.0": 8.42,
        "168.0": 8.54,
        "175.0": 8.66,
        "193.0": 7.48,
        "209.0": 7.81,
        "223.0": 7.23,
        "225.0": 7.18,
        "238.0": 7.39,
        "242.0": 7.44,
        "253.0": 6.85,
        "266.0": 7.05,
        "284.0": 6.61,
        "286.0": 6.65,
        "299.0": 6.81,
        "314.0": 6.41,
        "330.0": 6.58,
        "335.0": 6.49,
        "351.0": 6.02,
        "361.0": 5.84,
        "377.0": 5.5,
        "405.0": 5.01,
        "420.0": 4.94,
        "440.0": 4.87,
        "452.0": 4.83,
        "462.0": 4.8,
        "480.0": 4.75,
        "501.0": 4.7,
        "531.0": 4.63,
        "540.0": 4.61,
        "559.0": 4.57,
        "592.0": 4.51,
        "630.0": 4.45,
        "650.0": 4.42,
        "666.0": 4.4,
        "690.0": 4.38,
        "726.0": 4.38,
        "769.0": 4.38,
        "781.0": 4.38,
        "818.0": 4.38,
        "865.0": 4.37,
        "900.0": 4.37,
        "930.0": 4.37,
        "960.0": 4.37,
        "1000.0": 4.37,
        "1044.0": 4.37,
        "1082.0": 4.37,
        "1110.0": 4.37,
        "1140.0": 4.37,
        "1183.0": 4.42,
        "1229.0": 4.45,
        "1320.0": 4.53,
        "1411.0": 4.59,
        "1456.0": 4.62,
        "1548.0": 4.68,
        "1642.0": 4.72,
        "1733.0": 4.77,
        "1800.0": 4.79,
        "1867.0": 4.82,
        "2007.0": 4.77,
        "2140.0": 4.73,
        "2188.0": 4.72,
        "2232.0": 4.71,
        "2372.0": 4.68,
        "2461.0": 4.66,
        "2520.0": 4.65,
        "2597.0": 4.63,
        "2737.0": 4.65,
        "2870.0": 4.67,
        "2962.0": 4.69,
        "3102.0": 4.71,
        "3238.0": 4.72,
        "3329.0": 4.73,
        "3469.0": 4.75,
        "3602.0": 4.76,
        "3786.0": 4.78,
        "3877.0": 4.79,
        "3966.0": 4.79,
        "4151.0": 4.81,
        "4242.0": 4.81,
        "4331.0": 4.82,
        "4516.0": 4.82,
        "4607.0": 4.82,
        "4697.0": 4.82,
        "4883.0": 4.82,
        "4976.0": 4.82,
        "5062.0": 4.82,
        "5247.0": 4.82,
        "5338.0": 4.82,
        "5429.0": 4.82,
        "5580.0": 4.82,
        "5703.0": 4.82,
        "5884.0": 4.82,
        "6068.0": 4.82,
        "6250.0": 4.82,
        "6434.0": 4.82,
        "6615.0": 4.82,
        "6803.0": 4.82,
        "6980.0": 4.82,
        "7165.0": 4.82,
        "7253.0": 4.82,
        "7438.0": 4.82,
        "7620.0": 4.82,
        "7804.0": 4.82,
        "7984.0": 4.82,
        "8260.0": 4.82,
        "8625.0": 4.82,
        "8994.0": 4.82,
        "9174.0": 4.82,
        "9538.0": 4.82,
        "9902.0": 4.82,
        "11638.0": 4.82
    }
}