{
    "2024-04-25": {
        "1.0": 10.65,
        "5.0": 10.66,
        "14.0": 2.28,
        "21.0": 1.7,
        "27.0": 3.58,
        "33.0": 4.8,
        "36.0": 5.26,
        "48.0": 3.96,
        "53.0": 3.5,
        "57.0": 3.3,
        "63.0": 3.94,
        "67.0": 4.08,
        "83.0": 4.12,
        "90.0": 4.13,
        "97.0": 4.58,
        "111.0": 4.8,
        "113.0": 4.93,
        "126.0": 5.46,
        "130.0": 5.49,
        "144.0": 5.33,
        "147.0": 5.29,
        "151.0": 5.26,
        "159.0": 5.45,
        "173.0": 5.29,
        "180.0": 5.49,
        "190.0": 5.28,
        "207.0": 5.04,
        "218.0": 5.21,
        "237.0": 4.76,
        "242.0": 4.86,
        "249.0": 4.98,
        "265.0": 4.33,
        "281.0": 4.35,
        "293.0": 4.29,
        "300.0": 4.25,
        "309.0": 4.45,
        "326.0": 4.19,
        "335.0": 4.13,
        "341.0": 4.19,
        "362.0": 3.77,
        "372.0": 2.91,
        "390.0": 1.92,
        "400.0": 2.02,
        "421.0": 2.18,
        "432.0": 2.26,
        "452.0": 2.4,
        "475.0": 2.55,
        "480.0": 2.58,
        "491.0": 2.65,
        "510.0": 2.76,
        "524.0": 2.83,
        "540.0": 2.91,
        "571.0": 3.04,
        "601.0": 3.16,
        "617.0": 3.21,
        "664.0": 3.36,
        "697.0": 3.46,
        "720.0": 3.52,
        "781.0": 3.66,
        "810.0": 3.73,
        "844.0": 3.8,
        "889.0": 3.95,
        "930.0": 4.07,
        "960.0": 4.15,
        "991.0": 4.22,
        "1026.0": 4.3,
        "1071.0": 4.41,
        "1110.0": 4.49,
        "1140.0": 4.5,
        "1170.0": 4.5,
        "1208.0": 4.5,
        "1300.0": 4.5,
        "1391.0": 4.5,
        "1440.0": 4.5,
        "1530.0": 4.5,
        "1621.0": 4.54,
        "1713.0": 4.6,
        "1803.0": 4.66,
        "1894.0": 4.72,
        "1938.0": 4.77,
        "2078.0": 4.91,
        "2160.0": 4.99,
        "2211.0": 5.03,
        "2303.0": 5.11,
        "2443.0": 5.07,
        "2520.0": 5.05,
        "2668.0": 5.01,
        "2808.0": 4.98,
        "2881.0": 4.97,
        "3035.0": 4.94,
        "3175.0": 5.05,
        "3240.0": 5.09,
        "3399.0": 5.18,
        "3539.0": 5.23,
        "3602.0": 5.25,
        "3764.0": 5.31,
        "3904.0": 5.35,
        "3960.0": 5.37,
        "4129.0": 5.38,
        "4269.0": 5.37,
        "4320.0": 5.37,
        "4495.0": 5.36,
        "4635.0": 5.35,
        "4768.0": 5.34,
        "4953.0": 5.33,
        "5040.0": 5.33,
        "5135.0": 5.32,
        "5318.0": 5.32,
        "5401.0": 5.31,
        "5499.0": 5.31,
        "5590.0": 5.3,
        "5774.0": 5.3,
        "5956.0": 5.29,
        "6140.0": 5.29,
        "6321.0": 5.29,
        "6509.0": 5.29,
        "6686.0": 5.29,
        "6871.0": 5.29,
        "7053.0": 5.29,
        "7200.0": 5.29,
        "7326.0": 5.29,
        "7510.0": 5.29,
        "7690.0": 5.29,
        "7966.0": 5.29,
        "8331.0": 5.29,
        "8700.0": 5.29,
        "9000.0": 5.29,
        "9244.0": 5.29,
        "9608.0": 5.29,
        "11344.0": 5.29,
        "4.0": 10.66,
        "7.0": 7.44,
        "20.0": 1.05,
        "22.0": 2.26,
        "32.0": 4.54,
        "34.0": 5.04,
        "39.0": 5.46,
        "50.0": 3.64,
        "56.0": 3.12,
        "60.0": 3.47,
        "64.0": 4.08,
        "81.0": 4.11,
        "89.0": 4.13,
        "96.0": 4.49,
        "98.0": 4.66,
        "112.0": 4.87,
        "120.0": 5.24,
        "127.0": 5.51,
        "141.0": 5.34,
        "146.0": 5.3,
        "148.0": 5.27,
        "158.0": 5.49,
        "168.0": 5.17,
        "174.0": 5.34,
        "189.0": 5.3,
        "202.0": 5.09,
        "210.0": 5.0,
        "221.0": 5.17,
        "239.0": 4.83,
        "246.0": 4.95,
        "252.0": 5.04,
        "270.0": 4.42,
        "284.0": 4.34,
        "298.0": 4.26,
        "308.0": 4.42,
        "314.0": 4.48,
        "330.0": 4.05,
        "340.0": 4.21,
        "356.0": 4.03,
        "369.0": 3.15,
        "385.0": 1.88,
        "392.0": 1.94,
        "419.0": 2.17,
        "428.0": 2.24,
        "446.0": 2.36,
        "461.0": 2.46,
        "477.0": 2.57,
        "490.0": 2.65,
        "508.0": 2.74,
        "515.0": 2.78,
        "538.0": 2.9,
        "553.0": 2.97,
        "600.0": 3.16,
        "602.0": 3.17,
        "630.0": 3.26,
        "690.0": 3.44,
        "706.0": 3.49,
        "750.0": 3.6,
        "797.0": 3.7,
        "840.0": 3.79,
        "872.0": 3.89,
        "901.0": 3.98,
        "935.0": 4.08,
        "984.0": 4.2,
        "1021.0": 4.29,
        "1050.0": 4.36,
        "1082.0": 4.43,
        "1117.0": 4.5,
        "1162.0": 4.5,
        "1201.0": 4.5,
        "1254.0": 4.5,
        "1348.0": 4.5,
        "1439.0": 4.5,
        "1481.0": 4.5,
        "1573.0": 4.5,
        "1666.0": 4.57,
        "1757.0": 4.63,
        "1846.0": 4.69,
        "1924.0": 4.76,
        "2031.0": 4.87,
        "2122.0": 4.96,
        "2167.0": 4.99,
        "2258.0": 5.07,
        "2398.0": 5.08,
        "2489.0": 5.06,
        "2576.0": 5.04,
        "2762.0": 4.99,
        "2853.0": 4.97,
        "2944.0": 4.96,
        "3127.0": 5.01,
        "3218.0": 5.08,
        "3308.0": 5.14,
        "3492.0": 5.21,
        "3583.0": 5.25,
        "3672.0": 5.28,
        "3857.0": 5.34,
        "3948.0": 5.36,
        "4037.0": 5.39,
        "4222.0": 5.38,
        "4313.0": 5.37,
        "4403.0": 5.36,
        "4589.0": 5.35,
        "4682.0": 5.35,
        "4862.0": 5.34,
        "5002.0": 5.33,
        "5044.0": 5.33,
        "5226.0": 5.32,
        "5366.0": 5.31,
        "5409.0": 5.31,
        "5580.0": 5.3,
        "5683.0": 5.3,
        "5864.0": 5.29,
        "6049.0": 5.29,
        "6229.0": 5.29,
        "6416.0": 5.29,
        "6594.0": 5.29,
        "6780.0": 5.29,
        "6959.0": 5.29,
        "7144.0": 5.29,
        "7235.0": 5.29,
        "7417.0": 5.29,
        "7601.0": 5.29,
        "7782.0": 5.29,
        "8147.0": 5.29,
        "8512.0": 5.29,
        "8880.0": 5.29,
        "9062.0": 5.29,
        "9427.0": 5.29,
        "10800.0": 5.29,
        "13262.0": 5.29
    }
}