{
    "2006-01-20": {
        "3.0": 16.62,
        "31.0": 16.57,
        "60.0": 16.14,
        "90.0": 16.26,
        "122.0": 15.7,
        "164.0": 15.65,
        "210.0": 15.82,
        "255.0": 15.62,
        "300.0": 15.44,
        "347.0": 15.29,
        "390.0": 15.31,
        "437.0": 15.16,
        "480.0": 15.08,
        "528.0": 15.04,
        "570.0": 15.03,
        "619.0": 14.98,
        "661.0": 14.89,
        "712.0": 14.78,
        "752.0": 14.71,
        "802.0": 14.71,
        "840.0": 14.67,
        "893.0": 14.62,
        "930.0": 14.64,
        "985.0": 14.65,
        "1020.0": 14.64,
        "1078.0": 14.6,
        "1110.0": 14.57,
        "1167.0": 14.53,
        "1200.0": 14.46,
        "1350.0": 14.42,
        "1445.0": 14.34,
        "1802.0": 14.18,
        "1988.0": 14.1,
        "2173.0": 14.04,
        "2539.0": 13.93,
        "2904.0": 13.86,
        "3269.0": 13.81,
        "4380.0": 13.66,
        "12.0": 16.28,
        "40.0": 15.85,
        "73.0": 16.21,
        "102.0": 15.69,
        "150.0": 15.61,
        "180.0": 15.74,
        "241.0": 15.61,
        "270.0": 15.56,
        "332.0": 15.39,
        "360.0": 15.27,
        "420.0": 15.22,
        "451.0": 15.12,
        "510.0": 15.07,
        "542.0": 15.03,
        "600.0": 15.01,
        "633.0": 14.94,
        "690.0": 14.84,
        "720.0": 14.79,
        "780.0": 14.72,
        "810.0": 14.71,
        "871.0": 14.61,
        "900.0": 14.63,
        "962.0": 14.63,
        "990.0": 14.64,
        "1050.0": 14.65,
        "1081.0": 14.58,
        "1140.0": 14.54,
        "1172.0": 14.52,
        "1258.0": 14.44,
        "1440.0": 14.36,
        "1623.0": 14.27,
        "1809.0": 14.18,
        "2160.0": 14.04,
        "2520.0": 13.95,
        "2880.0": 13.87,
        "3240.0": 13.82,
        "3601.0": 13.76
    }
}