{
    "2010-06-01": {
        "1.0": 9.27,
        "30.0": 9.89,
        "62.0": 10.01,
        "90.0": 10.34,
        "120.0": 10.56,
        "136.0": 10.64,
        "181.0": 10.61,
        "216.0": 10.79,
        "240.0": 11.03,
        "300.0": 11.15,
        "318.0": 11.31,
        "360.0": 11.39,
        "395.0": 11.47,
        "420.0": 11.52,
        "482.0": 11.65,
        "503.0": 11.67,
        "540.0": 11.69,
        "580.0": 11.74,
        "601.0": 11.78,
        "660.0": 11.85,
        "685.0": 11.84,
        "720.0": 11.88,
        "762.0": 11.93,
        "780.0": 11.97,
        "840.0": 11.97,
        "867.0": 11.96,
        "902.0": 11.93,
        "946.0": 11.92,
        "960.0": 11.93,
        "1021.0": 11.92,
        "1049.0": 11.92,
        "1080.0": 11.93,
        "1126.0": 11.93,
        "1170.0": 11.96,
        "1218.0": 11.97,
        "1311.0": 11.97,
        "1400.0": 11.98,
        "1441.0": 11.96,
        "1505.0": 11.98,
        "1597.0": 12.03,
        "1689.0": 12.05,
        "1779.0": 12.04,
        "1856.0": 12.04,
        "1948.0": 12.06,
        "2043.0": 12.04,
        "2131.0": 12.05,
        "2162.0": 12.04,
        "2236.0": 12.05,
        "2330.0": 12.05,
        "2421.0": 12.06,
        "2512.0": 12.05,
        "2589.0": 12.04,
        "2680.0": 12.05,
        "2772.0": 12.04,
        "2862.0": 12.03,
        "2880.0": 12.04,
        "2967.0": 12.03,
        "3058.0": 12.03,
        "3150.0": 12.02,
        "3240.0": 12.02,
        "3331.0": 12.01,
        "3423.0": 12.03,
        "3515.0": 12.02,
        "3600.0": 12.03,
        "3683.0": 12.02,
        "3775.0": 12.04,
        "3870.0": 12.03,
        "3957.0": 12.06,
        "3971.0": 12.06,
        "4062.0": 12.09,
        "4154.0": 12.12,
        "4248.0": 12.14,
        "4322.0": 12.14,
        "4413.0": 12.14,
        "4507.0": 12.14,
        "4598.0": 12.14,
        "4682.0": 12.14,
        "4703.0": 12.14,
        "4794.0": 12.14,
        "4885.0": 12.14,
        "5400.0": 12.14,
        "14.0": 9.02,
        "44.0": 10.1,
        "76.0": 10.2,
        "92.0": 10.45,
        "122.0": 10.66,
        "150.0": 10.74,
        "210.0": 10.79,
        "230.0": 10.9,
        "272.0": 11.15,
        "304.0": 11.24,
        "330.0": 11.22,
        "391.0": 11.4,
        "409.0": 11.53,
        "450.0": 11.64,
        "489.0": 11.67,
        "510.0": 11.68,
        "570.0": 11.76,
        "594.0": 11.77,
        "631.0": 11.79,
        "671.0": 11.84,
        "692.0": 11.85,
        "750.0": 11.92,
        "776.0": 11.94,
        "811.0": 11.97,
        "853.0": 11.98,
        "870.0": 11.98,
        "930.0": 11.94,
        "959.0": 11.93,
        "990.0": 11.92,
        "1035.0": 11.91,
        "1050.0": 11.92,
        "1112.0": 11.92,
        "1140.0": 11.93,
        "1200.0": 11.98,
        "1232.0": 11.98,
        "1324.0": 11.97,
        "1414.0": 11.99,
        "1491.0": 11.98,
        "1583.0": 12.02,
        "1676.0": 12.05,
        "1765.0": 12.05,
        "1800.0": 12.03,
        "1870.0": 12.04,
        "1962.0": 12.05,
        "2054.0": 12.05,
        "2145.0": 12.05,
        "2222.0": 12.05,
        "2316.0": 12.06,
        "2407.0": 12.05,
        "2498.0": 12.06,
        "2520.0": 12.05,
        "2603.0": 12.05,
        "2694.0": 12.05,
        "2785.0": 12.04,
        "2876.0": 12.03,
        "2953.0": 12.03,
        "3044.0": 12.03,
        "3137.0": 12.02,
        "3226.0": 12.02,
        "3317.0": 12.01,
        "3409.0": 12.02,
        "3502.0": 12.02,
        "3592.0": 12.03,
        "3606.0": 12.02,
        "3697.0": 12.03,
        "3789.0": 12.03,
        "3881.0": 12.04,
        "3961.0": 12.05,
        "4048.0": 12.09,
        "4140.0": 12.12,
        "4234.0": 12.14,
        "4320.0": 12.14,
        "4339.0": 12.14,
        "4427.0": 12.14,
        "4521.0": 12.14,
        "4612.0": 12.14,
        "4689.0": 12.14,
        "4780.0": 12.13,
        "4871.0": 12.14,
        "5040.0": 12.13,
        "5580.0": 12.14
    }
}