{
    "2010-03-03": {
        "1.0": 8.55,
        "29.0": 9.09,
        "43.0": 8.81,
        "75.0": 8.74,
        "104.0": 8.98,
        "134.0": 9.4,
        "166.0": 9.63,
        "182.0": 9.8,
        "212.0": 9.94,
        "240.0": 10.1,
        "300.0": 10.29,
        "320.0": 10.41,
        "362.0": 10.66,
        "394.0": 10.77,
        "420.0": 10.79,
        "481.0": 11.01,
        "499.0": 11.13,
        "540.0": 11.27,
        "579.0": 11.34,
        "600.0": 11.36,
        "660.0": 11.46,
        "684.0": 11.49,
        "721.0": 11.54,
        "761.0": 11.62,
        "782.0": 11.64,
        "840.0": 11.71,
        "866.0": 11.73,
        "901.0": 11.78,
        "943.0": 11.81,
        "960.0": 11.81,
        "1020.0": 11.79,
        "1049.0": 11.79,
        "1080.0": 11.8,
        "1125.0": 11.81,
        "1140.0": 11.83,
        "1202.0": 11.86,
        "1230.0": 11.88,
        "1322.0": 11.95,
        "1414.0": 12.02,
        "1490.0": 12.07,
        "1581.0": 12.05,
        "1673.0": 12.08,
        "1766.0": 12.09,
        "1800.0": 12.11,
        "1869.0": 12.12,
        "1960.0": 12.14,
        "2052.0": 12.18,
        "2144.0": 12.2,
        "2221.0": 12.22,
        "2312.0": 12.26,
        "2406.0": 12.3,
        "2497.0": 12.33,
        "2520.0": 12.35,
        "2602.0": 12.38,
        "2693.0": 12.42,
        "2784.0": 12.47,
        "2875.0": 12.5,
        "2952.0": 12.52,
        "3043.0": 12.56,
        "3134.0": 12.6,
        "3227.0": 12.61,
        "3316.0": 12.64,
        "3407.0": 12.66,
        "3499.0": 12.7,
        "3592.0": 12.72,
        "3605.0": 12.73,
        "3696.0": 12.75,
        "3787.0": 12.76,
        "3879.0": 12.79,
        "3971.0": 12.81,
        "4061.0": 12.89,
        "4152.0": 12.97,
        "4244.0": 13.05,
        "4324.0": 13.11,
        "4412.0": 13.12,
        "4503.0": 13.12,
        "4597.0": 13.12,
        "4681.0": 13.11,
        "4702.0": 13.12,
        "4793.0": 13.11,
        "4884.0": 13.11,
        "4975.0": 13.11,
        "5402.0": 13.12,
        "12.0": 8.33,
        "33.0": 8.35,
        "61.0": 8.51,
        "90.0": 8.96,
        "120.0": 9.21,
        "152.0": 9.5,
        "180.0": 9.74,
        "210.0": 9.89,
        "226.0": 9.99,
        "271.0": 10.1,
        "306.0": 10.31,
        "330.0": 10.52,
        "390.0": 10.7,
        "408.0": 10.85,
        "450.0": 10.96,
        "485.0": 11.07,
        "510.0": 11.14,
        "572.0": 11.32,
        "593.0": 11.34,
        "630.0": 11.38,
        "670.0": 11.45,
        "691.0": 11.5,
        "750.0": 11.61,
        "775.0": 11.62,
        "810.0": 11.66,
        "852.0": 11.71,
        "870.0": 11.76,
        "930.0": 11.8,
        "957.0": 11.79,
        "992.0": 11.77,
        "1036.0": 11.78,
        "1050.0": 11.79,
        "1111.0": 11.81,
        "1139.0": 11.82,
        "1170.0": 11.85,
        "1216.0": 11.87,
        "1308.0": 11.93,
        "1401.0": 12.01,
        "1440.0": 12.04,
        "1504.0": 12.07,
        "1595.0": 12.05,
        "1687.0": 12.08,
        "1779.0": 12.09,
        "1855.0": 12.12,
        "1946.0": 12.13,
        "2038.0": 12.18,
        "2133.0": 12.18,
        "2161.0": 12.2,
        "2235.0": 12.23,
        "2326.0": 12.27,
        "2420.0": 12.3,
        "2511.0": 12.34,
        "2588.0": 12.38,
        "2679.0": 12.41,
        "2770.0": 12.47,
        "2862.0": 12.49,
        "2882.0": 12.5,
        "2966.0": 12.53,
        "3057.0": 12.56,
        "3148.0": 12.6,
        "3240.0": 12.62,
        "3330.0": 12.64,
        "3421.0": 12.67,
        "3513.0": 12.71,
        "3600.0": 12.73,
        "3682.0": 12.75,
        "3773.0": 12.76,
        "3865.0": 12.79,
        "3960.0": 12.8,
        "4047.0": 12.88,
        "4138.0": 12.96,
        "4230.0": 13.05,
        "4320.0": 13.11,
        "4338.0": 13.11,
        "4429.0": 13.11,
        "4517.0": 13.12,
        "4611.0": 13.11,
        "4688.0": 13.12,
        "4779.0": 13.12,
        "4870.0": 13.11,
        "4961.0": 13.12,
        "5040.0": 13.11,
        "5580.0": 13.11
    }
}